pyrokit/__init__.py
pyrokit/progress.py
pyrokit-0.0.1.dist-info/LICENSE
pyrokit-0.0.1.dist-info/METADATA
pyrokit-0.0.1.dist-info/WHEEL
pyrokit-0.0.1.dist-info/top_level.txt
pyrokit-0.0.1.dist-info/RECORD
