Metadata-Version: 2.1
Name: pyrokit
Version: 0.0.1
Summary: The Complete Bot Builder Kit for Pyrogram Bots: Build, Enhance, and Scale with Ease
Home-page: https://github.com/nuhmanpk/pyrokit
Author: Nuhman Pk
Author-email: nuhmanpk7@gmail.com
License: MIT
Project-URL: Documentation, https://github.com/nuhmanpk/pyrokit/blob/main/README.md
Project-URL: Funding, https://github.com/sponsors/nuhmanpk
Project-URL: Source, https://github.com/nuhmanpk/pyrokit/
Project-URL: Tracker, https://github.com/nuhmanpk/pyrokit/issues
Platform: UNKNOWN
Classifier: Programming Language :: Python :: 3.9
Classifier: License :: OSI Approved :: MIT License
Classifier: Operating System :: OS Independent
Requires-Python: >=3.10
License-File: LICENSE
Requires-Dist: pyrogram
Requires-Dist: tgcrypto
